mesh/__init__.py
mesh/_manylinux.py
mesh/asm/__init__.py
mesh/boost/__init__.py
mesh/boost/contab.py
mesh/boost/disruptor.py
mesh/boost/mooter.py
mesh/boost/proxy.py
mesh/boost/remote.py
mesh/boost/ringbuffer.py
mesh/boost/runhook.py
mesh/boost/scheduler.py
mesh/cause/__init__.py
mesh/cause/errors.py
mesh/cause/status.py
mesh/codec/__init__.py
mesh/codec/codec.py
mesh/codec/former.py
mesh/codec/jsons.py
mesh/codec/protobuf.py
mesh/codec/tools.py
mesh/codec/xml.py
mesh/codec/yml.py
mesh/context/__init__.py
mesh/context/context.py
mesh/context/mesh.py
mesh/environ/__init__.py
mesh/environ/cache.py
mesh/environ/environ.py
mesh/examples/__init__.py
mesh/examples/consumer.py
mesh/examples/provider.py
mesh/grpx/__init__.py
mesh/grpx/bfia.py
mesh/grpx/bindservice.py
mesh/grpx/channels.py
mesh/grpx/consumer.py
mesh/grpx/interceptor.py
mesh/grpx/marshaller.py
mesh/grpx/provider.py
mesh/grpx/transport.py
mesh/http/__init__.py
mesh/http/consumer.py
mesh/http/provider.py
mesh/ioc/__init__.py
mesh/ioc/cause_handler.py
mesh/ioc/context.py
mesh/ioc/envs_processor.py
mesh/ioc/paas_processor.py
mesh/kinds/__init__.py
mesh/kinds/captcha.py
mesh/kinds/commerce.py
mesh/kinds/document.py
mesh/kinds/entity.py
mesh/kinds/environ.py
mesh/kinds/event.py
mesh/kinds/inbound.py
mesh/kinds/institution.py
mesh/kinds/license.py
mesh/kinds/location.py
mesh/kinds/meshflag.py
mesh/kinds/outbound.py
mesh/kinds/page.py
mesh/kinds/paging.py
mesh/kinds/principal.py
mesh/kinds/profile.py
mesh/kinds/reference.py
mesh/kinds/registration.py
mesh/kinds/route.py
mesh/kinds/script.py
mesh/kinds/service.py
mesh/kinds/timeout.py
mesh/kinds/versions.py
mesh/log/__init__.py
mesh/log/nop.py
mesh/log/types.py
mesh/macro/__init__.py
mesh/macro/ark.py
mesh/macro/binding.py
mesh/macro/cause.py
mesh/macro/codec.py
mesh/macro/compatible.py
mesh/macro/index.py
mesh/macro/inspect.py
mesh/macro/interface.py
mesh/macro/loader.py
mesh/macro/mpi.py
mesh/macro/mps.py
mesh/macro/proxy.py
mesh/macro/spi.py
mesh/macro/types.py
imesh-0.0.47.1.dist-info/LICENSE
imesh-0.0.47.1.dist-info/WHEEL
imesh-0.0.47.1.dist-info/METADATA
imesh-0.0.47.1.dist-info/RECORD
