Metadata-Version: 2.1
Name: imesh
Version: 0.0.47.1
Summary: A lightweight, distributed, relational network architecture for MPC.
Home-page: https://mesh.github.com
License: LICENSE
Keywords: servicemesh,rpc,cluster,registry,mesh
Author: coyzeng
Author-email: coyzeng@gmail.com
Maintainer: coyzeng
Maintainer-email: coyzeng@gmail.com
Requires-Python: >=3.7,<4.0
Classifier: Development Status :: 5 - Production/Stable
Classifier: License :: OSI Approved :: MIT License
Classifier: License :: Other/Proprietary License
Classifier: Natural Language :: English
Classifier: Operating System :: OS Independent
Classifier: Programming Language :: Python :: 3
Classifier: Programming Language :: Python :: 3.7
Classifier: Programming Language :: Python :: 3.8
Classifier: Programming Language :: Python :: 3.9
Classifier: Programming Language :: Python :: 3.10
Classifier: Programming Language :: Python :: 3.7
Classifier: Programming Language :: Python :: 3.8
Classifier: Programming Language :: Python :: 3.9
Classifier: Topic :: Software Development :: Libraries :: Python Modules
Requires-Dist: grpcio (>=1.43.0,<2.0.0)
Requires-Dist: opentelemetry-api (>=1.18.0,<2.0.0)
Requires-Dist: opentelemetry-exporter-otlp (>=1.18.0,<2.0.0)
Requires-Dist: opentelemetry-sdk (>=1.18.0,<2.0.0)
Requires-Dist: protobuf (>=3.14.0,<4.0.0)
Project-URL: Documentation, https://mesh.github.com/docs
Project-URL: Repository, https://mesh.github.com
